dasher/__init__.py
dasher/api.py
dasher/app.py
dasher/base.py
dasher/layout/__init__.py
dasher/layout/bootstrap/__init__.py
dasher/layout/bootstrap/layout.py
dasher/layout/bootstrap/min_max_value.py
dasher/layout/bootstrap/widgets.py
dasher-0.3.1.dist-info/AUTHORS.rst
dasher-0.3.1.dist-info/LICENSE
dasher-0.3.1.dist-info/METADATA
dasher-0.3.1.dist-info/WHEEL
dasher-0.3.1.dist-info/top_level.txt
dasher-0.3.1.dist-info/RECORD
