Metadata-Version: 2.1
Name: dasher
Version: 0.3.1
Summary: Generate interactive plotly dash dashboards in an instant
Home-page: https://github.com/mfaafm/dasher
Author: Martijn Arts
Author-email: m.arts@gmx.net
License: MIT
Project-URL: Documentation, https://dasher.readthedocs.io/
Project-URL: Changelog, https://dasher.readthedocs.io/en/latest/changelog.html
Project-URL: Issue Tracker, https://github.com/mfaafm/dasher/issues
Keywords: dashboard,plotly,dash,prototyping
Platform: UNKNOWN
Classifier: Development Status :: 3 - Alpha
Classifier: Intended Audience :: Developers
Classifier: License :: OSI Approved :: MIT License
Classifier: Operating System :: Unix
Classifier: Operating System :: POSIX
Classifier: Operating System :: Microsoft :: Windows
Classifier: Programming Language :: Python
Classifier: Programming Language :: Python :: 3
Classifier: Programming Language :: Python :: 3.6
Classifier: Programming Language :: Python :: 3.7
Classifier: Programming Language :: Python :: 3.8
Classifier: Programming Language :: Python :: Implementation :: CPython
Classifier: Programming Language :: Python :: Implementation :: PyPy
Classifier: Topic :: Utilities
Requires-Python: >=3.6
Requires-Dist: dash
Requires-Dist: dash-core-components
Requires-Dist: dash-html-components
Requires-Dist: dash-bootstrap-components (>=0.6)
